murano_dashboard-2015.1.1.dist-info/DESCRIPTION.rst
murano_dashboard-2015.1.1.dist-info/METADATA
murano_dashboard-2015.1.1.dist-info/RECORD
murano_dashboard-2015.1.1.dist-info/WHEEL
murano_dashboard-2015.1.1.dist-info/metadata.json
murano_dashboard-2015.1.1.dist-info/pbr.json
murano_dashboard-2015.1.1.dist-info/top_level.txt
muranodashboard/__init__.py
muranodashboard/dashboard.py
muranodashboard/exceptions.py
muranodashboard/middleware.py
muranodashboard/models.py
muranodashboard/version.py
muranodashboard/views.py
muranodashboard/api/__init__.py
muranodashboard/api/packages.py
muranodashboard/catalog/__init__.py
muranodashboard/catalog/forms.py
muranodashboard/catalog/panel.py
muranodashboard/catalog/tabs.py
muranodashboard/catalog/urls.py
muranodashboard/catalog/views.py
muranodashboard/categories/__init__.py
muranodashboard/categories/forms.py
muranodashboard/categories/panel.py
muranodashboard/categories/tables.py
muranodashboard/categories/urls.py
muranodashboard/categories/views.py
muranodashboard/common/__init__.py
muranodashboard/common/cache.py
muranodashboard/common/utils.py
muranodashboard/dynamic_ui/__init__.py
muranodashboard/dynamic_ui/fields.py
muranodashboard/dynamic_ui/forms.py
muranodashboard/dynamic_ui/helpers.py
muranodashboard/dynamic_ui/services.py
muranodashboard/dynamic_ui/version.py
muranodashboard/dynamic_ui/yaql_expression.py
muranodashboard/dynamic_ui/yaql_functions.py
muranodashboard/environments/__init__.py
muranodashboard/environments/api.py
muranodashboard/environments/consts.py
muranodashboard/environments/forms.py
muranodashboard/environments/panel.py
muranodashboard/environments/tables.py
muranodashboard/environments/tabs.py
muranodashboard/environments/topology.py
muranodashboard/environments/urls.py
muranodashboard/environments/views.py
muranodashboard/images/__init__.py
muranodashboard/images/forms.py
muranodashboard/images/panel.py
muranodashboard/images/tables.py
muranodashboard/images/urls.py
muranodashboard/images/views.py
muranodashboard/local/_50_murano.py
muranodashboard/local/__init__.py
muranodashboard/local/local_settings.py.example
muranodashboard/openstack/__init__.py
muranodashboard/openstack/common/__init__.py
muranodashboard/openstack/common/_i18n.py
