Metadata-Version: 2.0
Name: murano-dashboard
Version: 2015.1.1
Summary: The Murano Dashboard
Home-page: https://launchpad.net/murano
Author: Mirantis, Inc.
Author-email: murano-all@lists.openstack.org
License: Apache License, Version 2.0
Platform: UNKNOWN
Classifier: Development Status :: 5 - Production/Stable
Classifier: Framework :: Django
Classifier: Topic :: Internet :: WWW/HTTP
Classifier: Environment :: OpenStack
Classifier: Intended Audience :: Developers
Classifier: Intended Audience :: Information Technology
Classifier: License :: OSI Approved :: Apache Software License
Classifier: Operating System :: OS Independent
Classifier: Programming Language :: Python
Requires-Dist: PyYAML (>=3.1.0)
Requires-Dist: beautifulsoup4
Requires-Dist: django-floppyforms (>=1.1)
Requires-Dist: iso8601 (>=0.1.9)
Requires-Dist: pbr (!=0.7,>=0.6,<1.0)
Requires-Dist: python-muranoclient (>=0.5.6,<0.6.0)
Requires-Dist: six (>=1.9.0)
Requires-Dist: yaql (<0.3,>=0.2.6)
